nested_inside/__init__.py
nested_inside/nests.py
nested_inside-0.2.dist-info/LICENSE
nested_inside-0.2.dist-info/METADATA
nested_inside-0.2.dist-info/WHEEL
nested_inside-0.2.dist-info/top_level.txt
nested_inside-0.2.dist-info/RECORD
