Metadata-Version: 2.1
Name: nested-inside
Version: 0.2
Summary: A nested data structure for accessing and modifying values using a delimiter
Home-page: https://github.com/MrDebugger/nested_inside
Author: Ijaz Ur Rahim
Author-email: ijazkhan095@gmail.com
License: MIT
Keywords: parser,json,dict,nested,nested_dict,nested_list,nested_tuple,tuple,list,nested_inside
Platform: UNKNOWN
Classifier: Programming Language :: Python :: 3
Classifier: License :: OSI Approved :: MIT License
Classifier: Operating System :: OS Independent
Requires-Python: >=3.6
Requires-Dist: typing
